flask_modals2/__init__.py
flask_modals2/modal.py
flask_modals2/partial.py
flask_modals2/static/css/progressBarStyle.css
flask_modals2/static/js/main.js
flask_modals2/templates/modals/jstemplate.html
flask_modals2/templates/modals/modalMessages.html
flask_modals2/templates/modals/nprogress.html
flask_modals2-0.6.1.dist-info/licenses/LICENSE
flask_modals2-0.6.1.dist-info/METADATA
flask_modals2-0.6.1.dist-info/WHEEL
flask_modals2-0.6.1.dist-info/top_level.txt
flask_modals2-0.6.1.dist-info/RECORD
