Metadata-Version: 2.4
Name: flask-modals2
Version: 0.6.1
Summary: Use forms in Bootstrap modals with Flask > 2.3
Home-page: https://github.com/ldariva/flask-modals2
Author: Leandro Dariva Pinto
Author-email: Leandro Dariva Pinto <leandro.dariva@gmail.com>
License-Expression: MIT
Project-URL: Homepage, https://github.com/ldariva/flask-modals
Project-URL: Issues, https://github.com/ldariva/flask-modals/issues
Classifier: Programming Language :: Python :: 3
Classifier: Operating System :: OS Independent
Requires-Python: >=3.10
License-File: LICENSE
Requires-Dist: flask
Requires-Dist: jinja2
Dynamic: author
Dynamic: home-page
Dynamic: license-file
Dynamic: requires-python
